custom_secrets_manager/__init__.py
custom_secrets_manager/constants.py
custom_secrets_manager/encryption_helper.py
custom_secrets_manager/secrets_loader.py
custom_secrets_manager/starter_process.py
custom_secrets_manager/temp_log_cleanup.py
custom_secrets_manager/workflow_helper.py
custom_secrets_manager-1.1.0.dist-info/LICENSE
custom_secrets_manager-1.1.0.dist-info/METADATA
custom_secrets_manager-1.1.0.dist-info/WHEEL
custom_secrets_manager-1.1.0.dist-info/entry_points.txt
custom_secrets_manager-1.1.0.dist-info/top_level.txt
custom_secrets_manager-1.1.0.dist-info/RECORD
