Metadata-Version: 2.1
Name: custom-secrets-manager
Version: 1.1.0
Summary: A utility for managing secrets and API keys
Home-page: https://github.com/vvid643/custom_secrets_manager
Author: Vashishtha Vidyarthi
License: MIT
Classifier: Development Status :: 5 - Production/Stable
Classifier: Intended Audience :: Developers
Classifier: License :: OSI Approved :: MIT License
Classifier: Operating System :: OS Independent
Classifier: Programming Language :: Python
Classifier: Programming Language :: Python :: 3
Classifier: Programming Language :: Python :: 3.6
Classifier: Programming Language :: Python :: 3.7
Classifier: Programming Language :: Python :: 3.8
Classifier: Programming Language :: Python :: 3.9
License-File: LICENSE
Requires-Dist: anyconfig (==0.13.0)
Requires-Dist: cryptography (==41.0.1)
